[
  {
    "name": "Christian ",
    "moves": 12
  },
  {
    "name": "hhhh",
    "moves": 4
  },
  {
    "name": "draw",
    "moves": 20
  },
  {
    "name": "Anton",
    "moves": 21
  },
  {
    "name": "Anton",
    "moves": 4
  },
  {
    "name": "Fjanton",
    "moves": 4
  },
  {
    "name": "jasjd",
    "moves": 4
  },
  {
    "name": "asdasd",
    "moves": 4
  },
  {
    "name": "AndersTvå",
    "moves": 5
  },
  {
    "name": "dsad",
    "moves": 4
  },
  {
    "name": "dsad",
    "moves": 4
  },
  {
    "name": "dsad",
    "moves": 4
  },
  {
    "name": "dsad",
    "moves": 4
  },
  {
    "name": "dsad",
    "moves": 4
  },
  {
    "name": "dsad",
    "moves": 4
  },
  {
    "name": "dsad",
    "moves": 8
  },
  {
    "name": "dsad",
    "moves": 6
  },
  {
    "name": "dsad",
    "moves": 4
  },
  {
    "name": "dsad",
    "moves": 6
  },
  {
    "name": "dsad",
    "moves": 4
  },
  {
    "name": "dsad",
    "moves": 4
  },
  {
    "name": "dsad",
    "moves": 8
  },
  {
    "name": "dsad",
    "moves": 8
  },
  {
    "name": "Louise ",
    "moves": 4
  },
  {
    "name": "ddd",
    "moves": 4
  },
  {
    "name": "dsad",
    "moves": 8
  },
  {
    "name": "dsad",
    "moves": 8
  },
  {
    "name": "dsad",
    "moves": 16
  },
  {
    "name": "dsad",
    "moves": 8
  },
  {
    "name": "dsad",
    "moves": 8
  },
  {
    "name": "dsad",
    "moves": 8
  },
  {
    "name": "dsad",
    "moves": 8
  },
  {
    "name": "Eli",
    "moves": 4
  },
  {
    "name": "Eli",
    "moves": 4
  },
  {
    "name": "Eli",
    "moves": 4
  },
  {
    "name": "Eli",
    "moves": 4
  },
  {
    "name": "Hej",
    "moves": 4
  },
  {
    "name": "Hej",
    "moves": 4
  },
  {
    "name": "Hej",
    "moves": 4
  },
  {
    "name": "Hej",
    "moves": 4
  },
  {
    "name": "Hej",
    "moves": 4
  }
]